pynucastro/__init__.py
pynucastro/_version.py
pynucastro/mpi_utils.py
pynucastro/numba_util.py
pynucastro/utils.py
pynucastro/yt_utils.py
pynucastro/constants/__init__.py
pynucastro/constants/constants.py
pynucastro/eos/__init__.py
pynucastro/eos/degeneracy_parameter_bounds.py
pynucastro/eos/difference_utils.py
pynucastro/eos/electron_eos.py
pynucastro/eos/eos_components.py
pynucastro/eos/fermi_integrals.py
pynucastro/eos/quadrature_weights.py
pynucastro/eos/stellar_eos.py
pynucastro/library/#20180319default2#
pynucastro/library/20180319default2
pynucastro/library/README.md
pynucastro/library/b17-nnn-c14-wc12
pynucastro/library/c12-ag-o16-nac2
pynucastro/library/c12-c12a-ne20-cf88
pynucastro/library/c12-c12n-mg23-cf88
pynucastro/library/c12-c12p-na23-cf88
pynucastro/library/c12-gaa-he4-fy05
pynucastro/library/c12-pg-n13-ls09
pynucastro/library/c13-pg-n14-nacr
pynucastro/library/d-pg-he3-de04
pynucastro/library/f17--o17-wc12
pynucastro/library/f17-pg-ne18-cb09
pynucastro/library/f18--o18-wc12
pynucastro/library/f18-pa-o15-il10
pynucastro/library/f19-pa-o16-nacr
pynucastro/library/he3-he3pp-he4-nacr
pynucastro/library/he4-aag-c12-fy05
pynucastro/library/he4-npahe3-li7-mafo
pynucastro/library/he4-pphe3-he3-nacr
pynucastro/library/he4-pphe3-he3-nacr-historical
pynucastro/library/he6-gnn-he4-cf88
pynucastro/library/li7-tnna-he4-mafo
pynucastro/library/n--p-wc12
pynucastro/library/n13--c13-wc12
pynucastro/library/n13-pg-o14-lg06
pynucastro/library/n14-pg-o15-im05
pynucastro/library/n15-pa-c12-nacr
pynucastro/library/n15-pg-o16-li10
pynucastro/library/ne18--f18-wc12
pynucastro/library/o14--n14-wc12
pynucastro/library/o14-ap-f17-Ha96c
pynucastro/library/o15--n15-wc12
pynucastro/library/o16-pg-f17-ia08
pynucastro/library/o17-pa-n14-il10
pynucastro/library/o17-pg-f18-il10
pynucastro/library/o18-pa-n15-il10
pynucastro/library/o18-pg-f19-il10
pynucastro/library/p-ng-d-an06
pynucastro/library/p-p-d-ec
pynucastro/library/rate_sources.csv
pynucastro-2.9.0.dist-info/licenses/LICENSE
pynucastro-2.9.0.dist-info/METADATA
pynucastro-2.9.0.dist-info/WHEEL
pynucastro-2.9.0.dist-info/top_level.txt
pynucastro-2.9.0.dist-info/RECORD
