Metadata-Version: 2.4
Name: pynucastro
Version: 2.9.0
Summary: A python library for nuclear astrophysics
Author: pynucastro development group
Author-email: michael.zingale@stonybrook.edu
License-Expression: BSD-3-Clause
Project-URL: Homepage, https://github.com/pynucastro/pynucastro
Project-URL: Documentation, https://pynucastro.github.io/pynucastro/
License-File: LICENSE
Requires-Dist: networkx
Requires-Dist: numpy
Requires-Dist: sympy
Requires-Dist: scipy
Requires-Dist: matplotlib
Requires-Dist: ipywidgets
Provides-Extra: numba
Requires-Dist: numba; extra == "numba"
Dynamic: license-file
